setup.py
aioamqp/__init__.py
aioamqp/channel.py
aioamqp/compat.py
aioamqp/constants.py
aioamqp/envelope.py
aioamqp/exceptions.py
aioamqp/frame.py
aioamqp/properties.py
aioamqp/protocol.py
aioamqp/version.py
aioamqp_beta.egg-info/PKG-INFO
aioamqp_beta.egg-info/SOURCES.txt
aioamqp_beta.egg-info/dependency_links.txt
aioamqp_beta.egg-info/not-zip-safe
aioamqp_beta.egg-info/requires.txt
aioamqp_beta.egg-info/top_level.txt